whitewater/__init__.py
whitewater/__main__.py
whitewater/cli.py
whitewater/whitewater.py
whitewater-1.0.1.dist-info/DESCRIPTION.rst
whitewater-1.0.1.dist-info/entry_points.txt
whitewater-1.0.1.dist-info/METADATA
whitewater-1.0.1.dist-info/metadata.json
whitewater-1.0.1.dist-info/RECORD
whitewater-1.0.1.dist-info/top_level.txt
whitewater-1.0.1.dist-info/WHEEL
