Metadata-Version: 2.0
Name: whitewater
Version: 1.0.1
Summary: Convert videos into a format readable by the Whitewater Player Javascript library.
Home-page: https://github.com/samiare/whitewater-encoder
Author: Samir Zahran
Author-email: sayhello@samiare.net
License: MIT
Keywords: video mobile
Platform: UNKNOWN
Classifier: Development Status :: 5 - Production/Stable
Classifier: Environment :: Console
Classifier: Intended Audience :: Developers
Classifier: License :: OSI Approved :: MIT License
Classifier: Programming Language :: Python :: 2.7
Classifier: Topic :: Multimedia :: Video
Classifier: Topic :: Utilities
Requires-Dist: docopt (>=0.6.2)
Requires-Dist: imageio (>=1.4)
Requires-Dist: numpy (>=1.10.2)
Requires-Dist: Pillow (>=3.0.0)
